steinbock/__init__.py
steinbock/__main__.py
steinbock/_env.py
steinbock/_steinbock.py
steinbock/_version.py
steinbock/io.py
steinbock/visualization.py
steinbock/_cli/__init__.py
steinbock/_cli/_cli.py
steinbock/_cli/apps.py
steinbock/_cli/utils.py
steinbock/_cli/visualization.py
steinbock/classification/__init__.py
steinbock/classification/_classification.py
steinbock/classification/_cli/__init__.py
steinbock/classification/_cli/_cli.py
steinbock/classification/_cli/ilastik.py
steinbock/classification/ilastik/__init__.py
steinbock/classification/ilastik/_ilastik.py
steinbock/classification/ilastik/data/__init__.py
steinbock/classification/ilastik/data/pixel_classifier.ilp
steinbock/export/__init__.py
steinbock/export/data.py
steinbock/export/graphs.py
steinbock/export/_cli/__init__.py
steinbock/export/_cli/_cli.py
steinbock/export/_cli/data.py
steinbock/export/_cli/graphs.py
steinbock/measurement/__init__.py
steinbock/measurement/_measurement.py
steinbock/measurement/intensities.py
steinbock/measurement/neighbors.py
steinbock/measurement/regionprops.py
steinbock/measurement/_cli/__init__.py
steinbock/measurement/_cli/_cli.py
steinbock/measurement/_cli/cellprofiler.py
steinbock/measurement/_cli/intensities.py
steinbock/measurement/_cli/neighbors.py
steinbock/measurement/_cli/regionprops.py
steinbock/measurement/cellprofiler/__init__.py
steinbock/measurement/cellprofiler/_cellprofiler.py
steinbock/measurement/cellprofiler/data/__init__.py
steinbock/measurement/cellprofiler/data/cell_measurement.cppipe
steinbock/preprocessing/__init__.py
steinbock/preprocessing/_preprocessing.py
steinbock/preprocessing/external.py
steinbock/preprocessing/imc.py
steinbock/preprocessing/_cli/__init__.py
steinbock/preprocessing/_cli/_cli.py
steinbock/preprocessing/_cli/external.py
steinbock/preprocessing/_cli/imc.py
steinbock/segmentation/__init__.py
steinbock/segmentation/_segmentation.py
steinbock/segmentation/cellpose.py
steinbock/segmentation/deepcell.py
steinbock-0.16.3.dist-info/LICENSE
steinbock-0.16.3.dist-info/METADATA
steinbock-0.16.3.dist-info/WHEEL
steinbock-0.16.3.dist-info/entry_points.txt
steinbock-0.16.3.dist-info/top_level.txt
steinbock-0.16.3.dist-info/zip-safe
steinbock-0.16.3.dist-info/RECORD
