Metadata-Version: 2.1
Name: steinbock
Version: 0.16.3
Summary: A toolkit for processing multiplexed tissue images
Home-page: https://github.com/BodenmillerGroup/steinbock
Author: Jonas Windhager
Author-email: jonas@windhager.io
Maintainer: Milad Adibi
Maintainer-email: milad.adibi@uzh.ch
License: MIT
Classifier: Operating System :: OS Independent
Classifier: Programming Language :: Python :: 3
Classifier: Programming Language :: Python :: 3.8
Classifier: Programming Language :: Python :: 3.9
Classifier: License :: OSI Approved :: MIT License
Requires-Python: >=3.8
License-File: LICENSE
Requires-Dist: anndata
Requires-Dist: click
Requires-Dist: click-log
Requires-Dist: fcswrite
Requires-Dist: h5py
Requires-Dist: imageio
Requires-Dist: networkx
Requires-Dist: numpy
Requires-Dist: opencv-python-headless
Requires-Dist: pandas
Requires-Dist: scikit-image
Requires-Dist: scipy
Requires-Dist: tifffile
Requires-Dist: xtiff
Provides-Extra: cellpose
Requires-Dist: cellpose ; extra == 'cellpose'
Provides-Extra: deepcell
Requires-Dist: deepcell ; extra == 'deepcell'
Requires-Dist: pyyaml ; extra == 'deepcell'
Provides-Extra: imc
Requires-Dist: readimc ; extra == 'imc'
Provides-Extra: napari
Requires-Dist: napari[all] ; extra == 'napari'
